<annotation><filename>img_513184122.jpg</filename><folder>users/pixtract/dataset</folder><source><database>submitted</database><software>LabelMe Webtool</software><submittedBy>pixtract</submittedBy><author>Robert Nagy</author><description/><originalFilename>DSC_0452.JPG</originalFilename></source><owner><name>Anders Dicker</name><chair>FAU - CS 6 - Data Management</chair></owner><properties><width>3008</width><height>2000</height><depth>8/16</depth><brightness>98.1106</brightness><contrast>58.8252</contrast></properties><object><text>SEP</text><deleted>0</deleted><verified>0</verified><date>07-Oct-2010 10:39:45</date><id>0</id><optical><texture>low</texture><brightness>66.2848</brightness><contrast inverted="true">35.8631</contrast><resolution>2708.3333333333335</resolution><noise>low</noise><blurredness>8.14342</blurredness></optical><geometrical><distortion><sx>1.01754385964912</sx><sy>0.892307692307692</sy><rx>-0.056</rx><ry>0</ry><tx>0</tx><ty>7</ty><px>0.000140350877192982</px><py>0</py></distortion><rotation>3.43363036245059</rotation><arrangement>horizontal</arrangement><cover>0</cover></geometrical><typographical><font>standard</font><language>abbreviation</language></typographical><difficult>false</difficult><polygon><username>pixtract</username><pt><x>1752</x><y>244</y></pt><pt><x>1877</x><y>244</y></pt><pt><x>1877</x><y>309</y></pt><pt><x>1752</x><y>309</y></pt></polygon></object><object><text>20</text><deleted>0</deleted><verified>0</verified><date>07-Oct-2010 10:39:45</date><id>1</id><optical><texture>low</texture><brightness>60.136</brightness><contrast inverted="true">37.2882</contrast><resolution>2720</resolution><noise>low</noise><blurredness>5.73045</blurredness></optical><geometrical><distortion><sx>1.01785714285714</sx><sy>0.890625</sy><rx>-0.0823529411764706</rx><ry>0</ry><tx>0</tx><ty>7</ty><px>0.000210084033613445</px><py>0</py></distortion><rotation>5.0424510691708</rotation><arrangement>horizontal</arrangement><cover>0</cover></geometrical><typographical><font>standard</font><language>numbers</language></typographical><difficult>false</difficult><polygon><username>pixtract</username><pt><x>1960</x><y>234</y></pt><pt><x>2045</x><y>234</y></pt><pt><x>2045</x><y>298</y></pt><pt><x>1960</x><y>298</y></pt></polygon></object><object><text>MON</text><deleted>0</deleted><verified>0</verified><date>07-Oct-2010 10:39:45</date><id>2</id><optical><texture>low</texture><brightness>56.4589</brightness><contrast inverted="true">36.2668</contrast><resolution>3652</resolution><noise>low</noise><blurredness>10.2142</blurredness></optical><geometrical><distortion><sx>0.966666666666667</sx><sy>0.878787878787879</sy><rx>-0.0481927710843374</rx><ry>0</ry><tx>0</tx><ty>8</ty><px>-0.000200803212851406</px><py>0</py></distortion><rotation>2.41465652085093</rotation><arrangement>horizontal</arrangement><cover>0</cover></geometrical><typographical><font>standard</font><language>abbreviation</language></typographical><difficult>false</difficult><polygon><username>pixtract</username><pt><x>2123</x><y>223</y></pt><pt><x>2289</x><y>223</y></pt><pt><x>2289</x><y>289</y></pt><pt><x>2123</x><y>289</y></pt></polygon></object><object><text>EIZO</text><deleted>0</deleted><verified>0</verified><date>07-Oct-2010 10:39:45</date><id>3</id><optical><texture>low</texture><brightness>105.469</brightness><contrast inverted="false">13.56</contrast><resolution>864</resolution><noise>low</noise><blurredness>10.2155</blurredness></optical><geometrical><distortion><sx>0.994152046783626</sx><sy>0.315789473684211</sy><rx>0.491228070175439</rx><ry>-0.166666666666667</ry><tx>8</tx><ty>0</ty><px>0.00146198830409357</px><py>-0.00109649122807018</py></distortion><rotation>332.700427788667</rotation><arrangement>horizontal</arrangement><cover>0</cover></geometrical><typographical><font>standard</font><language>company</language></typographical><difficult>false</difficult><polygon><username>pixtract</username><pt><x>2703</x><y>1754</y></pt><pt><x>2775</x><y>1754</y></pt><pt><x>2775</x><y>1802</y></pt><pt><x>2703</x><y>1802</y></pt></polygon></object></annotation>