<annotation><filename>img_357353819.jpg</filename><folder>users/pixtract/dataset</folder><source><database>submitted</database><software>LabelMe Webtool</software><submittedBy>pixtract</submittedBy><author>Robert Nagy</author><description/><originalFilename>DSCN3415.JPG</originalFilename></source><owner><name>Anders Dicker</name><chair>FAU - CS 6 - Data Management</chair></owner><properties><width>1200</width><height>1600</height><depth>8/16</depth><brightness>147.413</brightness><contrast>61.3412</contrast></properties><object><text>800 Jahre Hl. Elisabeth</text><deleted>0</deleted><verified>0</verified><date>07-Oct-2010 12:40:42</date><id>0</id><optical><texture>low</texture><brightness>165.507</brightness><contrast inverted="true">40.633</contrast><resolution>142.08695652173913</resolution><noise>low</noise><blurredness>5.77172</blurredness></optical><geometrical><distortion><sx>1</sx><sy>0.789473684210526</sy><rx>0.0232558139534884</rx><ry>0</ry><tx>0</tx><ty>0</ty><px>0</px><py>0</py></distortion><rotation>358.66778014613</rotation><arrangement>horizontal</arrangement><cover>0</cover></geometrical><typographical><font>standard</font><language>german</language></typographical><difficult>false</difficult><polygon><username>pixtract</username><pt><x>470</x><y>1400</y></pt><pt><x>642</x><y>1400</y></pt><pt><x>642</x><y>1419</y></pt><pt><x>470</x><y>1419</y></pt></polygon></object></annotation>