<annotation><filename>img_686809156.jpg</filename><folder>users/pixtract/dataset</folder><source><database>submitted</database><software>LabelMe Webtool</software><submittedBy>pixtract</submittedBy><author>Robert Nagy</author><description/><originalFilename>b_kk_2008-10-01_06.jpg</originalFilename></source><owner><name>Anders Dicker</name><chair>FAU - CS 6 - Data Management</chair></owner><properties><width>768</width><height>1152</height><depth>8/16</depth><brightness>156.633</brightness><contrast>70.7943</contrast></properties><object><text>HOTEL PALOTA</text><deleted>0</deleted><verified>0</verified><date>27-Sep-2010 19:39:37</date><id>0</id><optical><texture>low</texture><brightness>171.757</brightness><contrast inverted="false">76.1563</contrast><resolution>90</resolution><noise>low</noise><blurredness>1.52377</blurredness></optical><geometrical><distortion><sx>1.11111111111111</sx><sy>0.666666666666667</sy><rx>0.0925925925925926</rx><ry>0</ry><tx>0</tx><ty>0</ty><px>0.00154320987654321</px><py>0</py></distortion><rotation>355.631722565412</rotation><arrangement>horizontal</arrangement><cover>0</cover></geometrical><typographical><font>standard</font><language>company</language></typographical><difficult>false</difficult><polygon><username>pixtract</username><pt><x>506</x><y>689</y></pt><pt><x>578</x><y>689</y></pt><pt><x>578</x><y>704</y></pt><pt><x>506</x><y>704</y></pt></polygon></object><object><text>TERASZ-&lt;br/&gt;NVITVA</text><deleted>0</deleted><verified>0</verified><date>27-Sep-2010 19:39:37</date><id>1</id><optical><texture>low</texture><brightness>196.506</brightness><contrast inverted="false">56.7301</contrast><resolution>71.99999999999999</resolution><noise>low</noise><blurredness>1.35807</blurredness></optical><geometrical><distortion><sx>1.05555555555556</sx><sy>0.904761904761905</sy><rx>0.0659722222222222</rx><ry>0</ry><tx>0</tx><ty>0</ty><px>0.00115740740740741</px><py>0</py></distortion><rotation>357.018538780018</rotation><arrangement>horizontal</arrangement><cover>0</cover></geometrical><typographical><font>standard</font><language>hungarian</language></typographical><difficult>false</difficult><polygon><username>pixtract</username><pt><x>497</x><y>700</y></pt><pt><x>545</x><y>700</y></pt><pt><x>545</x><y>721</y></pt><pt><x>497</x><y>721</y></pt></polygon></object><object><text>TERRACE&lt;br/&gt;-OPEN</text><deleted>0</deleted><verified>0</verified><date>27-Sep-2010 19:39:37</date><id>2</id><optical><texture>low</texture><brightness>190.693</brightness><contrast inverted="false">56.0323</contrast><resolution>71.07692307692308</resolution><noise>low</noise><blurredness>0.990991</blurredness></optical><geometrical><distortion><sx>1.11764705882353</sx><sy>0.904761904761905</sy><rx>0.101604278074866</rx><ry>0</ry><tx>0</tx><ty>0</ty><px>0.00267379679144385</px><py>0</py></distortion><rotation>356.099506257618</rotation><arrangement>horizontal</arrangement><cover>0</cover></geometrical><typographical><font>standard</font><language>english</language></typographical><difficult>false</difficult><polygon><username>pixtract</username><pt><x>543</x><y>702</y></pt><pt><x>587</x><y>702</y></pt><pt><x>587</x><y>723</y></pt><pt><x>543</x><y>723</y></pt></polygon></object></annotation>