<annotation><filename>img_143371697.jpg</filename><folder>users/pixtract/dataset</folder><source><database>submitted</database><software>LabelMe Webtool</software><submittedBy>pixtract</submittedBy><author>Robert Nagy</author><description/><originalFilename>london_0707_141.jpg</originalFilename></source><owner><name>Anders Dicker</name><chair>FAU - CS 6 - Data Management</chair></owner><properties><width>1536</width><height>2048</height><depth>8/16</depth><brightness>91.8204</brightness><contrast>65.0391</contrast></properties><object><text>Royal Obersatory Greenwich</text><deleted>0</deleted><verified>0</verified><date>20-Sep-2010 11:34:44</date><id>0</id><optical><texture>low</texture><brightness>102.602</brightness><contrast inverted="true">60.26</contrast><resolution>1636.962962962963</resolution><noise>mid</noise><blurredness>8.10524</blurredness></optical><geometrical><distortion><sx>1.05420054200542</sx><sy>0.924136838770985</sy><rx>-0.0313588850174216</rx><ry>-0.0324675324675325</ry><tx>5</tx><ty>9</ty><px>0.000249554511473437</px><py>-0.000113127290827639</py></distortion><rotation>2.86751726923832</rotation><arrangement>horizontal</arrangement><cover>0</cover></geometrical><typographical><font>standard</font><language>english</language></typographical><difficult>false</difficult><polygon><username>pixtract</username><pt><x>496</x><y>230</y></pt><pt><x>783</x><y>230</y></pt><pt><x>783</x><y>384</y></pt><pt><x>496</x><y>384</y></pt></polygon></object><object><text>GALVANO-MAGNETIC CLOCK</text><deleted>0</deleted><verified>0</verified><date>20-Sep-2010 11:34:44</date><id>1</id><optical><texture>low</texture><brightness>202.669</brightness><contrast inverted="false">48.5637</contrast><resolution>1219.5</resolution><noise>low</noise><blurredness>6.02702</blurredness></optical><geometrical><distortion><sx>1</sx><sy>1</sy><rx>0</rx><ry>0</ry><tx>0</tx><ty>0</ty><px>0</px><py>0</py></distortion><rotation>0</rotation><arrangement>circular</arrangement><cover orientation="vertical">8</cover></geometrical><typographical><font>standard</font><language>english</language></typographical><difficult>false</difficult><polygon><username>pixtract</username><pt><x>571</x><y>949</y></pt><pt><x>842</x><y>949</y></pt><pt><x>842</x><y>1048</y></pt><pt><x>571</x><y>1048</y></pt></polygon></object><object><text>SHEPHERD</text><deleted>0</deleted><verified>0</verified><date>20-Sep-2010 11:34:44</date><id>2</id><optical><texture>low</texture><brightness>186.842</brightness><contrast inverted="false">44.9222</contrast><resolution>225.25</resolution><noise>low</noise><blurredness>3.30483</blurredness></optical><geometrical><distortion><sx>1</sx><sy>1</sy><rx>0</rx><ry>0</ry><tx>0</tx><ty>0</ty><px>0</px><py>0</py></distortion><rotation>0</rotation><arrangement>horizontal</arrangement><cover orientation="horizontal">3</cover></geometrical><typographical><font>standard</font><language>english</language></typographical><difficult>false</difficult><polygon><username>pixtract</username><pt><x>576</x><y>892</y></pt><pt><x>682</x><y>892</y></pt><pt><x>682</x><y>909</y></pt><pt><x>576</x><y>909</y></pt></polygon></object><object><text>PATENTEE</text><deleted>0</deleted><verified>0</verified><date>20-Sep-2010 11:34:44</date><id>3</id><optical><texture>low</texture><brightness>190.72</brightness><contrast inverted="false">42.7991</contrast><resolution>225.25</resolution><noise>low</noise><blurredness>3.74552</blurredness></optical><geometrical><distortion><sx>1</sx><sy>1</sy><rx>0</rx><ry>0</ry><tx>0</tx><ty>0</ty><px>0</px><py>0</py></distortion><rotation>0</rotation><arrangement>horizontal</arrangement><cover>0</cover></geometrical><typographical><font>standard</font><language>english</language></typographical><difficult>false</difficult><polygon><username>pixtract</username><pt><x>734</x><y>890</y></pt><pt><x>840</x><y>890</y></pt><pt><x>840</x><y>907</y></pt><pt><x>734</x><y>907</y></pt></polygon></object><object><text>53 LEADENHALL ST LONDON</text><deleted>0</deleted><verified>0</verified><date>20-Sep-2010 11:34:44</date><id>4</id><optical><texture>low</texture><brightness>170.177</brightness><contrast inverted="false">63.4139</contrast><resolution>126.78260869565217</resolution><noise>low</noise><blurredness>10.078</blurredness></optical><geometrical><distortion><sx>1</sx><sy>1</sy><rx>0</rx><ry>0</ry><tx>0</tx><ty>0</ty><px>0</px><py>0</py></distortion><rotation>0</rotation><arrangement>horizontal</arrangement><cover orientation="vertical">28</cover></geometrical><typographical><font>standard</font><language>english</language></typographical><difficult>false</difficult><polygon><username>pixtract</username><pt><x>587</x><y>920</y></pt><pt><x>830</x><y>920</y></pt><pt><x>830</x><y>932</y></pt><pt><x>587</x><y>932</y></pt></polygon></object><object><text>HEIGHT ABOVE MEAN SEA LEVEL AT NEWLYN 154-70 FEET.</text><deleted>0</deleted><verified>0</verified><date>20-Sep-2010 11:34:44</date><id>5</id><optical><texture>low</texture><brightness>207.974</brightness><contrast inverted="false">12.6327</contrast><resolution>128.34</resolution><noise>mid</noise><blurredness>5.86915</blurredness></optical><geometrical><distortion><sx>1</sx><sy>1</sy><rx>0</rx><ry>0</ry><tx>0</tx><ty>0</ty><px>0</px><py>0</py></distortion><rotation>0</rotation><arrangement>horizontal</arrangement><cover>0</cover></geometrical><typographical><font>standard</font><language>english</language></typographical><difficult>true</difficult><polygon><username>pixtract</username><pt><x>666</x><y>1317</y></pt><pt><x>759</x><y>1317</y></pt><pt><x>759</x><y>1386</y></pt><pt><x>666</x><y>1386</y></pt></polygon></object><object><text>BRITISH YARD</text><deleted>0</deleted><verified>0</verified><date>20-Sep-2010 11:34:44</date><id>6</id><optical><texture>low</texture><brightness>87.1247</brightness><contrast inverted="true">77.5477</contrast><resolution>306.6666666666667</resolution><noise>mid</noise><blurredness>3.60832</blurredness></optical><geometrical><distortion><sx>1.125</sx><sy>0.782608695652174</sy><rx>0.04921875</rx><ry>0</ry><tx>0</tx><ty>0</ty><px>0.00078125</px><py>0</py></distortion><rotation>357.852414571702</rotation><arrangement>horizontal</arrangement><cover>0</cover></geometrical><typographical><font>standard</font><language>english</language></typographical><difficult>false</difficult><polygon><username>pixtract</username><pt><x>613</x><y>1597</y></pt><pt><x>773</x><y>1597</y></pt><pt><x>773</x><y>1620</y></pt><pt><x>613</x><y>1620</y></pt></polygon></object><object><text>TWO FEET</text><deleted>0</deleted><verified>0</verified><date>20-Sep-2010 11:34:44</date><id>7</id><optical><texture>low</texture><brightness>89.0689</brightness><contrast inverted="true">76.0024</contrast><resolution>268.375</resolution><noise>mid</noise><blurredness>2.84068</blurredness></optical><geometrical><distortion><sx>0.933333333333333</sx><sy>0.736842105263158</sy><rx>0.0330383480825959</rx><ry>0</ry><tx>0</tx><ty>0</ty><px>-0.000589970501474926</px><py>0</py></distortion><rotation>357.719514675318</rotation><arrangement>horizontal</arrangement><cover orientation="horizontal">6</cover></geometrical><typographical><font>standard</font><language>english</language></typographical><difficult>false</difficult><polygon><username>pixtract</username><pt><x>636</x><y>1660</y></pt><pt><x>749</x><y>1660</y></pt><pt><x>749</x><y>1679</y></pt><pt><x>636</x><y>1679</y></pt></polygon></object></annotation>