<annotation><filename>img_77303996.jpg</filename><folder>users/pixtract/dataset</folder><source><database>submitted</database><software>LabelMe Webtool</software><submittedBy>pixtract</submittedBy><author>Anders Dicker</author><description/><originalFilename>1287_Porsche_gelb.JPG</originalFilename></source><owner><name>Anders Dicker</name><chair>FAU - CS 6 - Data Management</chair></owner><properties><width>2560</width><height>1920</height><depth>8/16</depth><brightness>112.214</brightness><contrast>45.8145</contrast></properties><object><text>54</text><deleted>0</deleted><verified>0</verified><date>10-Oct-2010 20:08:26</date><id>0</id><optical><texture>low</texture><brightness>91.5885</brightness><contrast inverted="false">54.6506</contrast><resolution>1950</resolution><noise>mid</noise><blurredness>5.73099</blurredness></optical><geometrical><distortion><sx>1</sx><sy>1</sy><rx>0</rx><ry>0</ry><tx>0</tx><ty>0</ty><px>0</px><py>0</py></distortion><rotation>0</rotation><arrangement>horizontal</arrangement><cover>0</cover></geometrical><typographical><font>standard</font><language>numbers</language></typographical><difficult>false</difficult><polygon><username>pixtract</username><pt><x>211</x><y>855</y></pt><pt><x>271</x><y>855</y></pt><pt><x>271</x><y>920</y></pt><pt><x>211</x><y>920</y></pt></polygon></object></annotation>