<annotation><filename>img_73672910.jpg</filename><folder>users/pixtract/dataset</folder><source><database>submitted</database><software>LabelMe Webtool</software><submittedBy>pixtract</submittedBy><author>Anders Dicker</author><description/><originalFilename>071_Kronplatz_Pistenraupe.JPG</originalFilename></source><owner><name>Anders Dicker</name><chair>FAU - CS 6 - Data Management</chair></owner><properties><width>2560</width><height>1920</height><depth>8/16</depth><brightness>126.762</brightness><contrast>78.8475</contrast></properties><object><text>CARABINIERI</text><deleted>0</deleted><verified>0</verified><date>11-Oct-2010 18:31:17</date><id>0</id><optical><texture>low</texture><brightness>166.378</brightness><contrast inverted="true">71.5806</contrast><resolution>11362.727272727272</resolution><noise>low</noise><blurredness>26.8342</blurredness></optical><geometrical><distortion><sx>1.03030303030303</sx><sy>0.937931034482759</sy><rx>-0.0104408352668213</rx><ry>0</ry><tx>0</tx><ty>9</ty><px>3.5154327497715e-05</px><py>0</py></distortion><rotation>0.731112954820043</rotation><arrangement>horizontal</arrangement><cover>0</cover></geometrical><typographical><font>standard</font><language>italian</language></typographical><difficult>false</difficult><polygon><username>pixtract</username><pt><x>30</x><y>969</y></pt><pt><x>892</x><y>969</y></pt><pt><x>892</x><y>1114</y></pt><pt><x>30</x><y>1114</y></pt></polygon></object></annotation>